{"cameraMode":{"drawMode":0,"name":"Shaded","section":"Shading Mode"},"sceneLighting":false,"audioPlay":false,"sceneViewState":{"showFog":true,"showMaterialUpdate":false,"showSkybox":false,"showFlares":true,"showImageEffects":true,"showParticleSystems":true},"in2DMode":false,"pivot":{"x":174.1917724609375,"y":9.752647399902344,"z":121.19337463378906},"rotation":{"x":-0.007234083488583565,"y":-0.9687601923942566,"z":0.2463335543870926,"w":-0.028481757268309594},"size":50.86146545410156,"orthographic":false}